data_visualizer/__init__.py
data_visualizer/__main__.py
data_visualizer/new_layout/__init__.py
data_visualizer/new_layout/open_file_layout.py
data_visualizer/util/__init__.py
data_visualizer/util/csv_data.py
data_visualizer/util/dict_functions.py
data_visualizer/util/errorHandling.py
data_visualizer/util/mysql_connection.py
data_visualizer/util/plot.py
data_visualizer/util/search_functions.py
data_visualizer/winds/__init__.py
data_visualizer/winds/connect_mysql_window.py
data_visualizer/winds/file_window.py
data_visualizer/winds/main_window.py
data_visualizer/winds/layouts/__init__.py
data_visualizer/winds/layouts/cmysql_layout.py
data_visualizer/winds/layouts/fw_layout.py
data_visualizer/winds/layouts/mw_layout.py
data_visualizer-0.1.7.dist-info/LICENSE.md
data_visualizer-0.1.7.dist-info/METADATA
data_visualizer-0.1.7.dist-info/WHEEL
data_visualizer-0.1.7.dist-info/entry_points.txt
data_visualizer-0.1.7.dist-info/top_level.txt
data_visualizer-0.1.7.dist-info/RECORD
